kinda/__init__.py
kinda/kinda.py
kinda/shim.py
kinda-0.9.9.dist-info/METADATA
kinda-0.9.9.dist-info/RECORD
kinda-0.9.9.dist-info/WHEEL
kinda-0.9.9.dist-info/top_level.txt
