Metadata-Version: 2.1
Name: kinda
Version: 0.9.9
Summary: A pythonic library for floating point number comparison
Home-page: https://github.com/schmamps/Kinda/
Author: Andrew Champion
Author-email: awchampion@gmail.com
License: UNKNOWN
Keywords: floating point,comparison
Platform: UNKNOWN
Classifier: Programming Language :: Python :: 2
Classifier: Programming Language :: Python :: 2.7
Classifier: Programming Language :: Python :: 3
Classifier: Programming Language :: Python :: 3.7
Classifier: License :: OSI Approved :: MIT License
Classifier: Operating System :: OS Independent
